{
 "custom_fields": [
  {
   "_assign": null,
   "_comments": null,
   "_liked_by": null,
   "_user_tags": null,
   "allow_in_quick_entry": 0,
   "allow_on_submit": 1,
   "bold": 0,
   "collapsible": 0,
   "collapsible_depends_on": null,
   "columns": 0,
   "creation": "2023-04-27 16:30:24.439122",
   "default": null,
   "depends_on": null,
   "description": null,
   "docstatus": 0,
   "dt": "BOM",
   "fetch_from": null,
   "fetch_if_empty": 0,
   "fieldname": "one_person",
   "fieldtype": "Float",
   "hidden": 0,
   "hide_border": 0,
   "hide_days": 0,
   "hide_seconds": 0,
   "idx": 12,
   "ignore_user_permissions": 0,
   "ignore_xss_filter": 0,
   "in_global_search": 0,
   "in_list_view": 0,
   "in_preview": 0,
   "in_standard_filter": 0,
   "insert_after": "quantity",
   "label": "One Person",
   "length": 0,
   "mandatory_depends_on": null,
   "modified": "2023-04-27 16:30:24.439122",
   "modified_by": "Administrator",
   "name": "BOM-one_person",
   "no_copy": 0,
   "non_negative": 0,
   "options": null,
   "owner": "Administrator",
   "parent": null,
   "parentfield": null,
   "parenttype": null,
   "permlevel": 0,
   "precision": "2",
   "print_hide": 0,
   "print_hide_if_no_value": 0,
   "print_width": null,
   "read_only": 1,
   "read_only_depends_on": null,
   "report_hide": 0,
   "reqd": 0,
   "search_index": 0,
   "translatable": 0,
   "unique": 0,
   "width": null
  },
  {
   "_assign": null,
   "_comments": null,
   "_liked_by": null,
   "_user_tags": null,
   "allow_in_quick_entry": 0,
   "allow_on_submit": 1,
   "bold": 0,
   "collapsible": 0,
   "collapsible_depends_on": null,
   "columns": 0,
   "creation": "2023-04-27 16:30:24.679558",
   "default": null,
   "depends_on": null,
   "description": null,
   "docstatus": 0,
   "dt": "BOM",
   "fetch_from": null,
   "fetch_if_empty": 0,
   "fieldname": "per_person",
   "fieldtype": "Float",
   "hidden": 0,
   "hide_border": 0,
   "hide_days": 0,
   "hide_seconds": 0,
   "idx": 13,
   "ignore_user_permissions": 0,
   "ignore_xss_filter": 0,
   "in_global_search": 0,
   "in_list_view": 0,
   "in_preview": 0,
   "in_standard_filter": 0,
   "insert_after": "one_person",
   "label": "Per Person",
   "length": 0,
   "mandatory_depends_on": null,
   "modified": "2023-04-27 16:30:24.679558",
   "modified_by": "Administrator",
   "name": "BOM-per_person",
   "no_copy": 0,
   "non_negative": 0,
   "options": null,
   "owner": "Administrator",
   "parent": null,
   "parentfield": null,
   "parenttype": null,
   "permlevel": 0,
   "precision": "1",
   "print_hide": 0,
   "print_hide_if_no_value": 0,
   "print_width": null,
   "read_only": 0,
   "read_only_depends_on": null,
   "report_hide": 0,
   "reqd": 0,
   "search_index": 0,
   "translatable": 0,
   "unique": 0,
   "width": null
  },
  {
   "_assign": null,
   "_comments": null,
   "_liked_by": null,
   "_user_tags": null,
   "allow_in_quick_entry": 0,
   "allow_on_submit": 1,
   "bold": 0,
   "collapsible": 0,
   "collapsible_depends_on": null,
   "columns": 0,
   "creation": "2023-04-27 16:30:24.873094",
   "default": null,
   "depends_on": null,
   "description": null,
   "docstatus": 0,
   "dt": "BOM",
   "fetch_from": null,
   "fetch_if_empty": 0,
   "fieldname": "bom_management_cost",
   "fieldtype": "Currency",
   "hidden": 0,
   "hide_border": 0,
   "hide_days": 0,
   "hide_seconds": 0,
   "idx": 14,
   "ignore_user_permissions": 0,
   "ignore_xss_filter": 0,
   "in_global_search": 0,
   "in_list_view": 0,
   "in_preview": 0,
   "in_standard_filter": 0,
   "insert_after": "per_person",
   "label": "BOM Management Cost",
   "length": 0,
   "mandatory_depends_on": null,
   "modified": "2023-04-27 16:30:24.873094",
   "modified_by": "Administrator",
   "name": "BOM-bom_management_cost",
   "no_copy": 0,
   "non_negative": 0,
   "options": "Company:company:default_currency",
   "owner": "Administrator",
   "parent": null,
   "parentfield": null,
   "parenttype": null,
   "permlevel": 0,
   "precision": "",
   "print_hide": 0,
   "print_hide_if_no_value": 0,
   "print_width": null,
   "read_only": 0,
   "read_only_depends_on": null,
   "report_hide": 0,
   "reqd": 0,
   "search_index": 0,
   "translatable": 0,
   "unique": 0,
   "width": null
  }
 ],
 "custom_perms": [],
 "doctype": "BOM",
 "property_setters": [],
 "sync_on_migrate": 1
}